torch_hawk.libs/libcudart-b5a066d7.so.12.2.140
torch_hawk-0.0.7.dist-info/top_level.txt
torch_hawk-0.0.7.dist-info/RECORD
torch_hawk-0.0.7.dist-info/LICENSE
torch_hawk-0.0.7.dist-info/METADATA
torch_hawk-0.0.7.dist-info/WHEEL
torch_hawk/__init__.py
torch_hawk/_torch_hawk.cpython-39-x86_64-linux-gnu.so
torch_hawk/py.typed
