Metadata-Version: 2.1
Name: torch_hawk
Version: 0.0.7
Summary: A Pythonic interface for MEDS datasets
License: Apache-2.0
Requires-Python: >=3.9
License-File: LICENSE
Requires-Dist: torch >=2
Requires-Dist: einops >=0.0.7
Requires-Dist: numpy
